mfacli/__init__.py
mfacli/__main__.py
mfacli/manage_totp.py
mfacli/mfa_cli.py
mfa_cli-0.3.5.dist-info/METADATA
mfa_cli-0.3.5.dist-info/WHEEL
mfa_cli-0.3.5.dist-info/entry_points.txt
mfa_cli-0.3.5.dist-info/top_level.txt
mfa_cli-0.3.5.dist-info/RECORD
